gigastep/__init__.py
gigastep-0.0.1.dist-info/METADATA
gigastep-0.0.1.dist-info/WHEEL
gigastep-0.0.1.dist-info/top_level.txt
gigastep-0.0.1.dist-info/RECORD
