Metadata-Version: 2.1
Name: gigastep
Version: 0.0.1
Summary: TODO
Home-page: https://github.com/
Author: Mathias Lechner
Author-email: mlechner@mit.edu
License: Apache Software License (Apache 2.0)
Platform: UNKNOWN
Classifier: Programming Language :: Python
Classifier: Programming Language :: Python :: 3.6
Classifier: Operating System :: Unix
Classifier: Operating System :: Microsoft :: Windows
Classifier: Operating System :: MacOS
Classifier: Intended Audience :: Science/Research
Classifier: Topic :: Scientific/Engineering
Classifier: Topic :: Software Development
Requires-Python: >3.6.0
Requires-Dist: future
Requires-Dist: numpy
Requires-Dist: packaging
